spacy_ann/__init__.py
spacy_ann/ann_linker.py
spacy_ann/candidate_generator.py
spacy_ann/models.py
spacy_ann/cli/__init__.py
spacy_ann/cli/create_index.py
spacy_ann-0.0.1.dist-info/entry_points.txt
spacy_ann-0.0.1.dist-info/LICENSE
spacy_ann-0.0.1.dist-info/WHEEL
spacy_ann-0.0.1.dist-info/METADATA
spacy_ann-0.0.1.dist-info/RECORD
