Metadata-Version: 2.1
Name: spacy_ann
Version: 0.0.1
Summary: spaCy ANN Linker, a pipeline component for generating spaCy KnowledgeBase Alias Candidates for Entity Linking.
Home-page: https://github.com/microsoft/spacy-ann-linker
License: UNKNOWN
Author: Kabir Khan
Author-email: kakh@microsoft.com
Requires-Python: >=3.6
Classifier: Intended Audience :: Information Technology
Classifier: Intended Audience :: System Administrators
Classifier: Operating System :: OS Independent
Classifier: Programming Language :: Python :: 3
Classifier: Programming Language :: Python
Classifier: Topic :: Software Development :: Libraries :: Application Frameworks
Classifier: Topic :: Software Development :: Libraries :: Python Modules
Classifier: Topic :: Software Development :: Libraries
Classifier: Topic :: Software Development
Classifier: Typing :: Typed
Classifier: Development Status :: 4 - Beta
Classifier: Intended Audience :: Developers
Classifier: Programming Language :: Python :: 3 :: Only
Classifier: Programming Language :: Python :: 3.6
Classifier: Programming Language :: Python :: 3.7
Classifier: Programming Language :: Python :: 3.8
Classifier: License :: OSI Approved :: MIT License
Requires-Dist: nmslib == 2.0.5
Requires-Dist: scikit-learn == 0.21.3
Requires-Dist: scipy >= 1.4.1, <1.5.0
Requires-Dist: spacy >= 2.2.1, <3.0.0
Requires-Dist: typer == 0.0.8
Requires-Dist: tqdm == 4.34.0
Requires-Dist: mkdocs ; extra == "doc"
Requires-Dist: mkdocs-material ; extra == "doc"
Requires-Dist: markdown-include ; extra == "doc"
Requires-Dist: click-completion ; extra == "test"
Requires-Dist: pytest >=4.4.0 ; extra == "test"
Requires-Dist: pytest-cov ; extra == "test"
Requires-Dist: coverage ; extra == "test"
Requires-Dist: pytest-xdist ; extra == "test"
Requires-Dist: pytest-sugar ; extra == "test"
Requires-Dist: mypy ; extra == "test"
Requires-Dist: black ; extra == "test"
Requires-Dist: isort ; extra == "test"
Project-URL: Documentation, https://typer.tiangolo.com/
Provides-Extra: doc
Provides-Extra: test
